crustal/__init__.py
crustal/catalog_utils.py
crustal/conf2str.py
crustal/station_utils.py
crustal/association/__init__.py
crustal/association/gamma_associator.py
crustal/graphics/__init__.py
crustal/graphics/plain_seismogram.py
crustal/graphics/sort_events_by_hand.py
crustal/graphics/tk_seismogram.py
crustal/graphs/__init__.py
crustal/graphs/seismogram.py
crustal/location/__init__.py
crustal/location/nll_locator.py
crustal/picking/__init__.py
crustal/picking/fdsnws_picker.py
crustal-0.2.1.dist-info/licenses/LICENSE
crustal-0.2.1.dist-info/METADATA
crustal-0.2.1.dist-info/WHEEL
crustal-0.2.1.dist-info/top_level.txt
crustal-0.2.1.dist-info/RECORD
