Metadata-Version: 2.4
Name: crustal
Version: 0.2.1
Summary: Crude Rough Unfinished Seismological Toolbox And Library
Author: attr: crustal.__author__
Author-email: Odysseus Galanis <ogalanis@geo.auth.gr>
License-Expression: GPL-3.0-or-later
Classifier: Programming Language :: Python :: 3
Classifier: Operating System :: OS Independent
Requires-Python: >=3.12
License-File: LICENSE
Dynamic: license-file
